drf_guard/__init__.py
drf_guard/operators.py
drf_guard/permissions.py
tests/testapp/__init__.py
tests/testapp/apps.py
tests/testapp/models.py
tests/testapp/permissions.py
tests/testapp/serializers.py
tests/testapp/views.py
tests/testapp/migrations/0001_initial.py
tests/testapp/migrations/__init__.py
drf_guard-0.3.0.dist-info/METADATA
drf_guard-0.3.0.dist-info/WHEEL
drf_guard-0.3.0.dist-info/top_level.txt
drf_guard-0.3.0.dist-info/RECORD
