Metadata-Version: 2.1
Name: drf-guard
Version: 0.3.0
Summary: Flexible permissions for Django REST Framework
Home-page: https://github.com/yezyilomo/drf-guard
Author: Yezy Ilomo
Author-email: yezileliilomo@hotmail.com
License: MIT
Platform: UNKNOWN
Classifier: Development Status :: 5 - Production/Stable
Classifier: Intended Audience :: Developers
Classifier: Natural Language :: English
Classifier: License :: OSI Approved :: MIT License
Classifier: Framework :: Django
Classifier: Framework :: Django :: 1.11
Classifier: Framework :: Django :: 2.0
Classifier: Framework :: Django :: 2.1
Classifier: Framework :: Django :: 2.2
Classifier: Framework :: Django :: 3.0
Classifier: Programming Language :: Python
Classifier: Programming Language :: Python :: 3.5
Classifier: Programming Language :: Python :: 3.6
Classifier: Programming Language :: Python :: 3.7
Classifier: Programming Language :: Python :: 3.8
Requires-Python: >=3.5
Requires-Dist: django (>=1.11)
Requires-Dist: djangorestframework (>=3.5)
